sample_lib/__init__.py
sample_lib/sum.py
sample_lib-0.1.dist-info/METADATA
sample_lib-0.1.dist-info/RECORD
sample_lib-0.1.dist-info/WHEEL
sample_lib-0.1.dist-info/top_level.txt
