Metadata-Version: 2.1
Name: sample-lib
Version: 0.1
Summary: A sample library that illustrates the usage of setup.py
Home-page: http://github.com/youssefsharief/python-setup-starter
Author: Youssef Sherif
Author-email: sharief@aucegypt.edu
License: MIT
Platform: UNKNOWN
